terrastorm/__init__.py
terrastorm/cli.py
terrastorm/services.py
terrastorm/settings.py
terrastorm/templates.py
terrastorm-0.0.4.dist-info/METADATA
terrastorm-0.0.4.dist-info/WHEEL
terrastorm-0.0.4.dist-info/entry_points.txt
terrastorm-0.0.4.dist-info/top_level.txt
terrastorm-0.0.4.dist-info/RECORD
