Metadata-Version: 2.1
Name: terrastorm
Version: 0.0.4
Summary: Use Terrastorm on Terraservices layout for terraform
Home-page: UNKNOWN
Author: Ross Crawford-d'Heureuse
Author-email: sendrossemail@gmail.com
License: MIT License
Platform: UNKNOWN
Classifier: Programming Language :: Python
Classifier: Programming Language :: Python :: 3
Requires-Dist: click
Requires-Dist: python-terraform
Requires-Dist: ruamel.yaml
Requires-Dist: pyhcl
Requires-Dist: cookiecutter
Requires-Dist: Jinja2
Requires-Dist: pebble
